napalm_inspector/__init__.py
napalm_inspector/drivers.py
napalm_inspector/exceptions.py
napalm_inspector/errors/__init__.py
napalm_inspector/errors/handlers.py
napalm_inspector/main/__init__.py
napalm_inspector/main/routes.py
napalm_inspector/static/favicon-default.ico
napalm_inspector/static/logo.png
napalm_inspector/static/napalm.css
napalm_inspector/templates/404.html
napalm_inspector/templates/base.html
napalm_inspector/templates/getter.html
napalm_inspector/templates/index.html
napalm_inspector/templates/platform.html
napalm_inspector/templates/test_getter_platforms.html
napalm_inspector-1.0.0.dist-info/LICENSE
napalm_inspector-1.0.0.dist-info/METADATA
napalm_inspector-1.0.0.dist-info/WHEEL
napalm_inspector-1.0.0.dist-info/top_level.txt
napalm_inspector-1.0.0.dist-info/RECORD
