Metadata-Version: 2.1
Name: napalm-inspector
Version: 1.0.0
Summary: Web application to test NAPALM getters
Home-page: https://github.com/napalm-automation/napalm-inspector
Author: Patrick Ogenstad
Author-email: patrick@ogenstad.com
License: UNKNOWN
Platform: UNKNOWN
Classifier: Topic :: Utilities
Classifier: Programming Language :: Python
Classifier: Programming Language :: Python :: 2
Classifier: Programming Language :: Python :: 2.7
Classifier: Programming Language :: Python :: 3
Classifier: Programming Language :: Python :: 3.4
Classifier: Programming Language :: Python :: 3.5
Classifier: Programming Language :: Python :: 3.6
Classifier: Operating System :: POSIX :: Linux
Classifier: Operating System :: MacOS
Requires-Dist: Flask (>=1.0.1)
Requires-Dist: napalm
